<?xml version="1.0" encoding="ISO-8859-1"?>
<Locality alone="true">
  <Details>
    <Detail>
      <nloc_cfti>080314.00</nloc_cfti>
      <desloc_cfti>Locarno</desloc_cfti>
      <provlet></provlet>
      <nazione>Switzerland</nazione>
      <risentimenti>6</risentimenti>
      <maxint>5</maxint>
      <lat_wgs84>46.171</lat_wgs84>
      <lon_wgs84>8.7931</lon_wgs84>
      <notesito></notesito>
    </Detail>
  </Details>
  <Quakes>
    <Quake>
      <cat>ITA</cat>
      <nterr>34811</nterr>
      <nperiod>003350</nperiod>
      <datanum>19630719</datanum>
      <data_label>1963 07 19</data_label>
      <anno>1963</anno>
      <mese>07</mese>
      <giorno>19</giorno>
      <time_label>05:45:28</time_label>
      <ora>05</ora>
      <minu>45</minu>
      <sec>28</sec>
      <lat>43.9233</lat>
      <lon>8.0648</lon>
      <rel></rel>
      <level>S</level>
      <io>6</io>
      <imax>6</imax>
      <npun>463</npun>
      <mm>5.4</mm>
      <earthquakelocation>Mar Ligure</earthquakelocation>
      <epicenter_type>Calculated epicentre</epicenter_type>
      <country>Italy</country>
      <ee_nt>0</ee_nt>
      <ee_np>0</ee_np>
      <flagcomments>3</flagcomments>
      <flagfalseeq></flagfalseeq>
      <intpqnum>4.6</intpqnum>
      <intpq>F</intpq>
      <D1/>
    </Quake>
    <Quake>
      <cat>ITA</cat>
      <nterr>39414</nterr>
      <nperiod>003126</nperiod>
      <datanum>19760915</datanum>
      <data_label>1976 09 15</data_label>
      <anno>1976</anno>
      <mese>09</mese>
      <giorno>15</giorno>
      <time_label>09:21:18</time_label>
      <ora>09</ora>
      <minu>21</minu>
      <sec>18</sec>
      <lat>46.2587</lat>
      <lon>13.1101</lon>
      <rel></rel>
      <level>S</level>
      <io>8.5</io>
      <imax>8.5</imax>
      <npun>54</npun>
      <mm>6.1</mm>
      <earthquakelocation>Friuli</earthquakelocation>
      <epicenter_type>Calculated epicentre</epicenter_type>
      <country>Italy</country>
      <ee_nt>0</ee_nt>
      <ee_np>46</ee_np>
      <flagcomments>4</flagcomments>
      <flagfalseeq></flagfalseeq>
      <intpqnum>4.6</intpqnum>
      <intpq>F</intpq>
      <D1>Il 15 settembre, alle 11:22 (9:22 GMT), fu avvertita una scossa $(090503)$.</D1>
    </Quake>
    <Quake>
      <cat>ITA</cat>
      <nterr>33063</nterr>
      <nperiod>000773</nperiod>
      <datanum>19510515</datanum>
      <data_label>1951 05 15</data_label>
      <anno>1951</anno>
      <mese>05</mese>
      <giorno>15</giorno>
      <time_label>22:54:24</time_label>
      <ora>22</ora>
      <minu>54</minu>
      <sec>24</sec>
      <lat>45.2521</lat>
      <lon>9.6005</lon>
      <rel></rel>
      <level>I</level>
      <io>6.5</io>
      <imax>6.5</imax>
      <npun>154</npun>
      <mm>5.4</mm>
      <earthquakelocation>Pianura Padana</earthquakelocation>
      <epicenter_type>Calculated epicentre</epicenter_type>
      <country>Italy</country>
      <ee_nt>0</ee_nt>
      <ee_np>0</ee_np>
      <flagcomments>3</flagcomments>
      <flagfalseeq></flagfalseeq>
      <intpqnum>4.5</intpqnum>
      <intpq>IV-V</intpq>
      <D1/>
    </Quake>
    <Quake>
      <cat>ITA</cat>
      <nterr>11384</nterr>
      <nperiod>003212</nperiod>
      <datanum>18800704</datanum>
      <data_label>1880 07 04</data_label>
      <anno>1880</anno>
      <mese>07</mese>
      <giorno>04</giorno>
      <time_label>19:55</time_label>
      <ora>19</ora>
      <minu>55</minu>
      <sec>-9</sec>
      <lat>46.2736</lat>
      <lon>8.059</lon>
      <rel></rel>
      <level>S</level>
      <io>7</io>
      <imax>7</imax>
      <npun>86</npun>
      <mm>5.4</mm>
      <earthquakelocation>Vallese</earthquakelocation>
      <epicenter_type>Calculated epicentre</epicenter_type>
      <country>Switzerland</country>
      <ee_nt>1</ee_nt>
      <ee_np>0</ee_np>
      <flagcomments>4</flagcomments>
      <flagfalseeq></flagfalseeq>
      <intpqnum>3</intpqnum>
      <intpq>III</intpq>
      <D1>La scossa fu avvertita leggermente $(001299,070240,095218)$.</D1>
    </Quake>
    <Quake>
      <cat>ITA</cat>
      <nterr>31050</nterr>
      <nperiod>003225</nperiod>
      <datanum>19341130</datanum>
      <data_label>1934 11 30</data_label>
      <anno>1934</anno>
      <mese>11</mese>
      <giorno>30</giorno>
      <time_label>02:58:23</time_label>
      <ora>02</ora>
      <minu>58</minu>
      <sec>23</sec>
      <lat>44.5562</lat>
      <lon>13.7224</lon>
      <rel></rel>
      <level>S</level>
      <io>5</io>
      <imax>5</imax>
      <npun>51</npun>
      <mm>5.2</mm>
      <earthquakelocation>Alto Adriatico</earthquakelocation>
      <epicenter_type>Calculated epicentre</epicenter_type>
      <country>Italy</country>
      <ee_nt>0</ee_nt>
      <ee_np>0</ee_np>
      <flagcomments>4</flagcomments>
      <flagfalseeq></flagfalseeq>
      <intpqnum>2.5</intpqnum>
      <intpq>II-III</intpq>
      <D1>La scossa fu avvertita leggermente $(090447)$.</D1>
    </Quake>
    <Quake>
      <cat>ITA</cat>
      <nterr>02067</nterr>
      <nperiod>003192</nperiod>
      <datanum>17551209</datanum>
      <data_label>1755 12 09</data_label>
      <anno>1755</anno>
      <mese>12</mese>
      <giorno>09</giorno>
      <time_label>13:30</time_label>
      <ora>13</ora>
      <minu>30</minu>
      <sec>-9</sec>
      <lat>46.316</lat>
      <lon>7.9849</lon>
      <rel></rel>
      <level>S</level>
      <io>8</io>
      <imax>8</imax>
      <npun>73</npun>
      <mm>5.9</mm>
      <earthquakelocation>Vallese</earthquakelocation>
      <epicenter_type>Calculated epicentre</epicenter_type>
      <country>Switzerland</country>
      <ee_nt>14</ee_nt>
      <ee_np>0</ee_np>
      <flagcomments>4</flagcomments>
      <flagfalseeq></flagfalseeq>
      <intpqnum>5</intpqnum>
      <intpq>V</intpq>
      <D1>La scossa fu avvertita fortemente $(000002)$.</D1>
    </Quake>
  </Quakes>
  <Biblios>
    <Bibliography>
      <codbib>090503</codbib>
      <autore1>*</autore1>
      <titolo1>ANSA Documentazione Elettronica, Notiziario italiano, maggio-settembre 1976.</titolo1>
      <luogoed>Roma</luogoed>
      <datacompl>1976</datacompl>
    </Bibliography>
    <Bibliography>
      <codbib>000002</codbib>
      <autore1>Mercalli G.</autore1>
      <titolo1>Vulcani e fenomeni vulcanici in Italia (ristampa anastatica, Sala Bolognese 1981).</titolo1>
      <luogoed>Milano</luogoed>
      <datacompl>1883</datacompl>
    </Bibliography>
    <Bibliography>
      <codbib>001299</codbib>
      <autore1>De Rossi M.S.</autore1>
      <titolo1>Quadri sinottici e cronologici dei fenomeni endogeni italiani col confronto di alcuni altri fenomeni [1º gennaio 1880-31 dicembre 1881], in "Bullettino del Vulcanismo Italiano", a.9, pp.47-68, 100-133.</titolo1>
      <luogoed>Roma</luogoed>
      <datacompl>1882</datacompl>
    </Bibliography>
    <Bibliography>
      <codbib>070240</codbib>
      <autore1>*</autore1>
      <titolo1>Terremoti del 4 luglio 1880, in "Bullettino Meteorologico dell’Osservatorio del Real Collegio Carlo Alberto in Moncalieri", vol.15 (1879-80), p.132.</titolo1>
      <luogoed>Torino</luogoed>
      <datacompl>1881</datacompl>
    </Bibliography>
    <Bibliography>
      <codbib>095218</codbib>
      <autore1>*</autore1>
      <titolo1>Terremoto del 4 Luglio [1880] dell’Alta Italia e di Svizzera (Lett[era] del ch[iarissimo] P.Denza ed altre notizie), in "Bullettino del Vulcanismo Italiano", a.7, pp.136-138.</titolo1>
      <luogoed>Roma</luogoed>
      <datacompl>1880</datacompl>
    </Bibliography>
    <Bibliography>
      <codbib>090447</codbib>
      <autore1>Caloi P.</autore1>
      <titolo1>Il terremoto adriatico del 30 Novembre 1934, in "Bollettino della Società Sismologica Italiana", vol.35 (1937), pp.93-119.</titolo1>
      <luogoed>Roma</luogoed>
      <datacompl>1937</datacompl>
    </Bibliography>
    <Bibliography>
      <codbib>052488</codbib>
      <autore1>BRGM (Bureau de Recherches Géologiques et Minières)</autore1>
      <titolo1>SisFrance: histoire et caractéristiques des séismes ressentis en France métropolitaine et sur ses abords, BRGM-EDF-IPSN [indirizzo internet: http://www.sisfrance.net].</titolo1>
      <luogoed></luogoed>
      <datacompl>2001</datacompl>
    </Bibliography>
  </Biblios>
</Locality>
