<?xml version="1.0" encoding="ISO-8859-1"?>
<Quake alone="true">
  <Details>
    <Detail>
      <data_label>1564 07 20</data_label>
      <time_label>18:30</time_label>
      <earthquakelocation>Alpi Marittime</earthquakelocation>
    </Detail>
  </Details>
  <Comments>
    <effects>
      <description>&lt;b&gt;Maggiori effetti del PERIODO SISMICO:&lt;/b&gt; &lt;br&gt; La scossa del 20 luglio 1564 danneggiò molto gravemente, causando crolli e rovine, una decina di località delle Alpi marittime, che attualmente rientrano nella regione francese di Provence-Côte d’Azur. Il terremoto si propagò ai centri liguri occidentali, da San Remo, a Taggia, a Porto Maurizio (ora parte di Imperia), con effetti di risentimento avvertiti anche nel cuneese. Non tutte le località menzionate dalle fonti sono state individuate (Rocca Marina, Sondalingi e Villaret risultano non localizzate).</description>
      <sequence>&lt;b&gt;Sequenza delle maggiori scosse del PERIODO SISMICO:&lt;/b&gt; &lt;br&gt; Sull’ora in cui avvenne la prima scossa non c’è accordo tra le fonti. Alcune relazioni tedesche indicano le ore 23 italiane, mentre quelle italiane indicano la prima o la seconda ora della notte; la discrepanza può dipendere sia dai diversi usi orari, sia dalle imprecisioni delle fonti $(000014)$. Le successive due repliche avvennero rispettivamente alle 6 (ora italiana) 1:30 GMT e poco prima dell’alba $(860061)$ intorno alle 4 GMT.</sequence>
    </effects>
  </Comments>
</Quake>
