<?xml version="1.0" encoding="ISO-8859-1"?>
<Quake alone="true">
  <Details>
    <Detail>
      <cat>ITA</cat>
      <nterr>32310</nterr>
      <nperiod>000565</nperiod>
      <datanum>19450614</datanum>
      <data_label>1945 06 14</data_label>
      <anno>1945</anno>
      <mese>06</mese>
      <giorno>14</giorno>
      <time_label>05:03:45</time_label>
      <ora>05</ora>
      <minu>03</minu>
      <sec>45</sec>
      <lat>44.818</lat>
      <lon>9.1456</lon>
      <rel></rel>
      <level>A</level>
      <io>6.5</io>
      <imax>6.5</imax>
      <npun>6</npun>
      <ee_nt>0</ee_nt>
      <ee_np>3</ee_np>
      <mm>4.9</mm>
      <earthquakelocation>Valle Staffora</earthquakelocation>
      <epicenter_type>Calculated epicentre</epicenter_type>
      <country>Italy</country>
      <flagcomments>4</flagcomments>
      <flagfalseeq></flagfalseeq>
      <new2018></new2018>
    </Detail>
  </Details>
  <Comments>
    <Comment>
      <codtab>B0</codtab>
      <testocomm>È stata revisionata la bibliografia del Catalogo ed è stata sviluppata una ricerca bibliografica e archivistica. Le ricerche sono state condotte in 16 sedi locali (archivi comunali e parrocchiali). Dalle pratiche amministrative sono state desunte notizie che hanno permesso di dettagliare e ampliare il quadro degli effetti; anche le ricerche svolte presso gli archivi parrocchiali dei paesi più colpiti hanno dato esito positivo: sono state reperite numerose notizie sui danni e sulle modalità della ricostruzione degli edifici di culto. Il particolare momento storico in cui accadde questo evento sismico ­ l’immediato secondo dopoguerra ­ condizionò sensibilmente la diffusione delle informazioni. Molti dei quotidiani nazionali avevano sospeso le pubblicazioni; la ricerca sulle fonti giornalistiche, di conseguenza, si è svolta su vari periodici a diffusione locale (12 testate). Per dettagliare le informazioni sono state utilizzate anche fonti orali: si tratta di interviste registrate (a cura di SGA) a persone che furono testimoni diretti dell’evento, i cui resoconti si sono dimostrati utili anche per la definizione del quadro sociale contestuale $(650180,710156,660023,660005,650054,650058,650059,650060,650061,650062,650063,650067,650068,650069,650070,650080,650081,650082,650083)$.</testocomm>
    </Comment>
    <Comment>
      <codtab>C0</codtab>
      <testocomm>Non ci furono vittime. L’evento aggravò i problemi della ricostruzione post-bellica in un’area collinare a prevalente economia agricola, caratterizzata dalla presenza di centri di fondovalle e piccoli insediamenti sparsi sulle pendici dei rilievi. I danni causati dal terremoto al patrimonio edilizio e alle infrastrutture produttive furono assorbiti inglobandoli nella generale situazione di emergenza $(660005,650058,650067,650069)$. Quest’ultima condizionò anche le modalità degli interventi per la riparazione dei danni, le cui denunce vennero raccolte dagli Uffici Tecnici comunali, e inviate al Genio Civile. Questo ente, in assenza di un centro di coordinamento amministrativo civile, assegnò il materiale edilizio necessario ai lavori di riparazione agli stessi Uffici Tecnici comunali che ne curarono la distribuzione ai privati $(650061,650062,650063,650081,650083,650071)$. Le difficoltà nell’opera di ricostruzione degli edifici distrutti sia dalla guerra sia dal terremoto derivarono soprattutto da due particolari contingenze: l’assenza di centri di potere locali e nazionali in grado di coordinare immediatamente le politiche d’intervento e il perdurare di una gravissima crisi economica. Quest’ultima era caratterizzata dalla penuria di generi di prima necessità e di materie prime $(650054)$. Proprio a causa della mancanza di materie prime per l’edilizia, quali il cemento e il ferro, erano in vigore norme restrittive che ne subordinavano l’acquisto alla concessione di speciali autorizzazioni.&lt;br&gt;Alcune testimonianze attestano che la grave situazione economica condizionò notevolmente i tempi e le modalità della ricostruzione; il parroco di Bagnaria, una delle località danneggiate, riportò in un diario manoscritto un sommario elenco dei danni e annotò con precisione i lavori di riparazione, i materiali usati e le spese. Questo resoconto offre la possibilità di valutare, seppure per un singolo edificio, quale fu la consistenza economica dei danni arrecati. Questi vennero stimati nella complessiva somma di 200.000 lire (la paga giornaliera di un muratore era di 350 lire e il prezzo di un quintale di cemento di 1.800 lire). Dalle poche notizie riportate sulla stampa locale si può desumere una valutazione abbastanza generica dell’ammontare complessivo dei danni, valutato nell’ordine di molti milioni di lire $(050021)$.</testocomm>
    </Comment>
    <Comment>
      <codtab>C2</codtab>
      <testocomm>Il terremoto accadde in località già danneggiate dalla guerra. Le operazioni belliche avevano assunto un carattere di grande distruttività nei primi mesi del 1945, causando rovine generalizzate nel patrimonio edilizio dell’area successivamente colpita dal terremoto $(660005,650058,650067,650069)$.</testocomm>
    </Comment>
    <Comment>
      <codtab>C3</codtab>
      <testocomm>Il patrimonio edilizio risultava già gravemente danneggiato dagli eventi bellici appena trascorsi, il terremoto aggravò le distruzioni apportate dalla guerra ai centri abitati $(660005,650058,650067,650069)$.</testocomm>
    </Comment>
    <Comment>
      <codtab>C4</codtab>
      <testocomm>L’evento sismico si verificò in un momento particolarmente travagliato. Da poche settimane si era concluso il secondo conflitto mondiale che aveva scompaginato la vita politica ed amministrativa. L’area interessata dall’evento sismico ricadeva sotto la giurisdizione del Comando Militare Alleato con sede a Pavia, che si avvaleva della collaborazione della Prefettura e del Comitato di Liberazione Nazionale dell’Alta Italia. Localmente gli unici organismi amministrativi che avevano conservato una presenza sul territorio erano i comuni, che tramite i loro uffici tecnici si incaricarono di censire i danni del terremoto; per quel che concerne l’aspetto tecnico, il provveditorato Regionale alle Opere Pubbliche della Lombardia e il Genio Civile svolsero un ruolo determinante soprattutto nella ripartizione degli aiuti ai centri danneggiati $(650054)$.</testocomm>
    </Comment>
    <Comment>
      <codtab>C5</codtab>
      <testocomm>La popolazione di Fabbrica Curone, Bagnaria e Gremiasco passò alcune notti all’aperto ma non si procedette alla costruzione di baracche $(660005,050021)$. Nei primi giorni di luglio il parroco di Bagnaria si rivolse al Genio Civile sollecitando la perizia dei danni alla chiesa, facendo richiesta di poter avere il materiale necessario alla riparazione a prezzi regolari. Egli prese contatti col Comandante Alleato di Voghera che gli assicurò il suo aiuto e ordinò che copia della perizia fosse inviata anche al Comando Alleato di Pavia. Come si può rilevare dal diario manoscritto dello stesso parroco, subito dopo il terremoto si svolsero cerimonie di ringraziamento e il denaro raccolto venne devoluto ai restauri alla chiesa; notevole fu la solidarietà della popolazione che prese parte ai lavori e in alcuni casi cedette parte del suo salario a favore della chiesa $(650054)$. Le autorità locali fecero presente al Genio Civile gli impedimenti a una regolare attività didattica derivanti dalle cattive condizioni degli edifici scolastici $(650070,650081)$.&lt;br&gt;Il sindaco di Varzi sollecitò l’intervento del Genio Civile per riparare i danni prodotti dalla guerra ed aggravati dal terremoto nella palestra delle scuole comunali e nell’asilo infantile $(650058,650068)$.&lt;br&gt;In occasione dell’anniversario del terremoto (29 giugno) si svolse per una decina di anni una funzione religiosa nell’oratorio di Colombassi $(660023)$.</testocomm>
    </Comment>
    <Comment>
      <codtab>C6</codtab>
      <testocomm>Le denunce dei danni del terremoto, raccolte dagli Uffici Tecnici comunali, vennero inviate al Genio Civile che assegnò il materiale edilizio necessario ai lavori di riparazione agli stessi Uffici Tecnici che ne curarono la distribuzione ai privati $(650061,650062,650063,650067,650080,650082,650071)$.&lt;br&gt;Nel dicembre del 1946 il sindaco di Varzi sollecitò un nuovo intervento del Genio Civile per ulteriori lavori alla palestra delle scuole comunali che, danneggiata dagli eventi bellici e lesionata dal terremoto, era già stata precedentemente riparata a cura dello stesso ufficio $(650058)$. La Giunta Municipale di Varzi deliberò nell’agosto del 1945 la riparazione dei danni causati dal terremoto al cimitero $(650059)$.</testocomm>
    </Comment>
    <Comment>
      <codtab>C7</codtab>
      <testocomm>La ricostruzione interessò non solo i danni del terremoto, ma anche e soprattutto quelli causati dagli eventi bellici $(660005,650058,650068,650069)$. Le denunce dei danni furono raccolte dagli Uffici Tecnici comunali e vennero inviate al Genio Civile, che assegnò il materiale edilizio necessario ai lavori di riparazione agli stessi Uffici Tecnici, questi ne curarono la distribuzione ai privati $(650061,650062,650063,650071)$. Il cemento, che scarseggiava sul mercato, non poteva essere acquistato senza una specifica autorizzazione $(650080)$. In alcuni casi, relativi soprattutto ad edifici pubblici, le riparazioni iniziarono con molto ritardo, anche a causa della mancanza di stanziamento di fondi da parte del Provveditorato Regionale alla Opere Pubbliche $(650081,650082,650083)$.&lt;br&gt;A Cecima i resti dell’edificio della canonica vennero demoliti dal Genio Civile $(650092)$. A Bagnaria i lavori di restauro della chiesa gravemente danneggiata durarono più di un anno $(650054)$. A Varzi i danni alle coperture e al piazzale del cimitero vennero riparati a spese del comune già nell’agosto del 1945 $(650060)$. Dallo studio della documentazione reperita si evince che il terremoto fu preso a pretesto, da alcuni cittadini, per ottenere finanziamenti per poter riparare edifici danneggiati dalla guerra.</testocomm>
    </Comment>
    <Comment>
      <codtab>C8</codtab>
      <testocomm>L’Ufficio Tecnico del Comune di Varzi stilò una perizia dei danni riportati dai fabbricati del cimitero del paese $(650060)$.</testocomm>
    </Comment>
    <Comment>
      <codtab>CA</codtab>
      <testocomm>Secondo la testimonianza del parroco di Cella dopo il terremoto un pozzo si prosciugò $(710156)$. In località Spizzirò si verificò la deviazione di una sorgente $(650071)$. Si riscontrarono variazioni nella portata delle sorgenti che fecero aumentare notevolmente la portata del rio Lanzola, affluente di destra della Staffora a valle di Varzi. Alcune testimonianze ricordarono l’intorbidamento temporaneo delle sorgenti successivo al terremoto $(080130)$.</testocomm>
    </Comment>
    <Comment>
      <codtab>D0</codtab>
      <testocomm>L’area colpita è localizzata nella zona preappenninica immediatamente a sud della piana dell’Oltrepò pavese. Le località più danneggiate furono Bagnaria, Cecima, Ponte Crenna, Ponte Nizza e San Ponzo Semola, situate nella media valle del torrente Staffora e nella parallela Val Curone. Lesioni di una certa entità agli edifici si riscontrarono anche a Gremiasco, San Sebastiano Curone, Varzi, Zavattarello e in alcune frazioni dei comuni di Bagnaria e Varzi $(080130)$. La presenza di notevoli danni agli edifici causati dagli eventi bellici, ha reso problematica la valutazione della reale portata degli effetti sismici $(660005)$.</testocomm>
    </Comment>
    <Comment>
      <codtab>E0</codtab>
      <testocomm>Furono osservate fenditure nel terreno argilloso dei versanti di alcuni rilievi tra le località di Varzi e Bagnaria. Da qualcuna di queste spaccature fuoriuscì fumo di odore acre; fu segnalata anche la comparsa di nuove sorgenti $(080130,050021)$.</testocomm>
    </Comment>
    <Comment>
      <codtab>F1</codtab>
      <testocomm>Una scossa di terremoto da collegarsi, con tutta probabilità, con il periodo sismico in studio fu registrata dagli strumenti dell’Osservatorio Geofisico di Pavia il 9 maggio 1945. Dall’inizio del mese di giugno 1945 furono avvertiti nella zona movimenti del suolo leggeri e frequenti. Il 14 giugno si registrò un primo massimo sismico caratterizzato da una forte scossa che ebbe come probabile area epicentrale la stessa zona che verrà poi danneggiata dal terremoto del 29 giugno. Sia le registrazioni strumentali che le testimonianze dirette non consento una precisa ricostruzione cronologica degli eventi in quanto sovente non era possibile distinguere tra i movimenti del suolo prodotti dallo scoppio di ordigni bellici e quelli originati dal succedersi delle scosse di terremoto $(080130,050021)$.&lt;br&gt;9 maggio 1945, ore 23:48 GMT circa: scossa di terremoto registrata dagli strumenti dell’Osservatorio Geofisico di Pavia $(080130)$.&lt;br&gt;14 giugno 1945, ore 5:03 GMT circa: forte scossa di avvertimento registrata dagli apparecchi dell’Osservatorio Geofisico di Pavia e avvertita nei territori di Bagnaria e Varzi; non si hanno notizie di danni $(080130)$.&lt;br&gt;28 giugno 1945, ore 18:09 GMT circa: scossa di terremoto registrata dagli strumenti dell’Osservatorio Geofisico di Pavia $(080130)$.&lt;br&gt;ore 18:49 GMT circa: scossa di terremoto registrata dagli strumenti dell’Osservatorio Geofisico di Pavia $(080130)$.&lt;br&gt;29 giugno 1945, ore 7:10 GMT circa: lieve scossa avvertita a Bagnaria $(650054)$.&lt;br&gt;ore 8:30 GMT circa: scossa forte che causò la caduta di calcinacci nella chiesa di Bagnaria $(650054,050021)$.&lt;br&gt;ore 15:37 GMT circa: scossa del V grado MCS avvertita a Pavia e registrata dagli strumenti dell’Osservatorio Geofisico $(650117)$.&lt;br&gt;30 giugno 1945, ore 4:33 GMT circa: replica registrata dagli strumenti dell’Osservatorio Geofisico di Pavia $(080130)$.</testocomm>
    </Comment>
  </Comments>
  <Biblios>
    <Bibliography>
      <codbib>021242</codbib>
      <autore1>SGA</autore1>
      <titolo1>Studi ed indagini per l’accertamento della idoneità tecnica delle aree suscettibili di insediamento di impianti nucleari. Regione Piemonte, Area Po2. Indagini di sismica storica: rapporto finale (inedito per ENEL).</titolo1>
      <luogoed></luogoed>
      <datacompl>1984</datacompl>
      <valb>Bs</valb>
      <desvalingl>Scientific bibliography</desvalingl>
    </Bibliography>
    <Bibliography>
      <codbib>050021</codbib>
      <autore1>*</autore1>
      <titolo1>Il Popolo Dertonino, 1945.07.07, a.50, n.9.</titolo1>
      <luogoed>Tortona</luogoed>
      <datacompl>1945</datacompl>
      <valb>Fi</valb>
      <desvalingl>Indirect source</desvalingl>
    </Bibliography>
    <Bibliography>
      <codbib>050045</codbib>
      <autore1>*</autore1>
      <titolo1>La Provincia Pavese, 1945.07.01, a.1, n.44.</titolo1>
      <luogoed>Pavia</luogoed>
      <datacompl>1945</datacompl>
      <valb>Fi</valb>
      <desvalingl>Indirect source</desvalingl>
    </Bibliography>
    <Bibliography>
      <codbib>080130</codbib>
      <autore1>Boni A.</autore1>
      <titolo1>I terremoti dell’Appennino vogherese-tortonese e la geologia della regione, in "Geofisica Pura e Applicata", vol.10, pp.114-143.</titolo1>
      <luogoed>Milano</luogoed>
      <datacompl>1947</datacompl>
      <valb>Bs</valb>
      <desvalingl>Scientific bibliography</desvalingl>
    </Bibliography>
    <Bibliography>
      <codbib>210045</codbib>
      <autore1>*</autore1>
      <titolo1>Cronache dell’Oltrepò. Organo del Comitato Liberazione Nazionale di Voghera, 1945.07.05.</titolo1>
      <luogoed>Voghera</luogoed>
      <datacompl>1945</datacompl>
      <valb>Fi</valb>
      <desvalingl>Indirect source</desvalingl>
    </Bibliography>
    <Bibliography>
      <codbib>240048</codbib>
      <autore1>Gribaudi D.</autore1>
      <titolo1>L’Agro Alessandrino nella storia in "Rivista di Storia, Arte, Archeologia per la Provincia di Alessandria", voll.78-79 (1969-70).</titolo1>
      <luogoed>Alessandria</luogoed>
      <datacompl>1969</datacompl>
      <valb>Fi</valb>
      <desvalingl>Indirect source</desvalingl>
    </Bibliography>
    <Bibliography>
      <codbib>240080</codbib>
      <autore1>Cortemiglia G.C.</autore1>
      <titolo1>Manifestazioni sismiche recenti nel tortonese, in "Julia Dertona", s.II, a.29, fasc.61, pp.5-22.</titolo1>
      <luogoed>Tortona</luogoed>
      <datacompl>1982</datacompl>
      <valb>Bs</valb>
      <desvalingl>Scientific bibliography</desvalingl>
    </Bibliography>
    <Bibliography>
      <codbib>640067</codbib>
      <autore1>*</autore1>
      <titolo1>Archivio Storico Comunale di Varzi, cat.10, cl.9, Lettera del Sindaco del comune di Varzi Grazzi M. all’Ingegnere Capo del Genio Civile di Pavia, Varzi 13 luglio 1945.</titolo1>
      <luogoed></luogoed>
      <datacompl>1945</datacompl>
      <valb>F</valb>
      <desvalingl>Direct source</desvalingl>
    </Bibliography>
    <Bibliography>
      <codbib>650054</codbib>
      <autore1>*</autore1>
      <titolo1>Archivio Parrocchiale dei Ss.Apostoli Pietro e Paolo di Livelli di Bagnaria, Miscellanea 1940-1955, Giuseppe Burrone Giuseppe, Appunti del parroco di Bagnaria Giuseppe Burrone sul terremoto del 1945 e sull’opera di ricostruzione della parrocchia di S.Bartolomeo Apostolo in Bagnaria comune di Varzi, 1945.</titolo1>
      <luogoed></luogoed>
      <datacompl>1945</datacompl>
      <valb>F</valb>
      <desvalingl>Direct source</desvalingl>
    </Bibliography>
    <Bibliography>
      <codbib>650058</codbib>
      <autore1>*</autore1>
      <titolo1>Archivio Storico Comunale di Varzi, cat.10, Lettera del Sindaco di Varzi Grazzi M. al Capo del Genio Civile di Pavia, Varzi 11 dicembre 1946.</titolo1>
      <luogoed></luogoed>
      <datacompl>1946</datacompl>
      <valb>F</valb>
      <desvalingl>Direct source</desvalingl>
    </Bibliography>
    <Bibliography>
      <codbib>650059</codbib>
      <autore1>*</autore1>
      <titolo1>Archivio Storico Comunale di Varzi, cat.10, Verbale di Deliberazione della Giunta Municipale del comune di Varzi, 21 agosto 1945.</titolo1>
      <luogoed></luogoed>
      <datacompl>1945</datacompl>
      <valb>F</valb>
      <desvalingl>Direct source</desvalingl>
    </Bibliography>
    <Bibliography>
      <codbib>650060</codbib>
      <autore1>*</autore1>
      <titolo1>Archivio Storico Comunale di Varzi, cat.10, cl.8, Relazione sui lavori di riparazione al manto di copertura degli stabili del cimitero nuovo e lavori di sgombro alla tubazione passante sotto il cimitero stesso, Varzi 14 agosto 1945.</titolo1>
      <luogoed></luogoed>
      <datacompl>1945</datacompl>
      <valb>F</valb>
      <desvalingl>Direct source</desvalingl>
    </Bibliography>
    <Bibliography>
      <codbib>650061</codbib>
      <autore1>*</autore1>
      <titolo1>Archivio Storico Comunale di Varzi, cat.10, cl.10, Avviso del Sindaco del comune di Varzi Grazzi M. ai proprietari degli stabili danneggiati dal terremoto del 1945.06.29, Varzi 1 luglio 1945.</titolo1>
      <luogoed></luogoed>
      <datacompl>1945</datacompl>
      <valb>F</valb>
      <desvalingl>Direct source</desvalingl>
    </Bibliography>
    <Bibliography>
      <codbib>650062</codbib>
      <autore1>*</autore1>
      <titolo1>Archivio Storico Comunale di Varzi, cat.10, cl.10, Avviso del Sindaco di Varzi Grazzi M. ai proprietari di stabili danneggiati dal terremoto del 29 giugno 1945, Varzi 1945.</titolo1>
      <luogoed></luogoed>
      <datacompl>1945</datacompl>
      <valb>F</valb>
      <desvalingl>Direct source</desvalingl>
    </Bibliography>
    <Bibliography>
      <codbib>650063</codbib>
      <autore1>*</autore1>
      <titolo1>Archivio Storico Comunale di Varzi, cat.10, Lettera dell’Ingegnere Capo del Genio Civile di Pavia Mariani G. al Sindaco del comune di Varzi, Pavia 17 settembre 1945.</titolo1>
      <luogoed></luogoed>
      <datacompl>1945</datacompl>
      <valb>F</valb>
      <desvalingl>Direct source</desvalingl>
    </Bibliography>
    <Bibliography>
      <codbib>650064</codbib>
      <autore1>*</autore1>
      <titolo1>Archivio Storico Comunale di Varzi, cat.10, Parcella delle competenze spettanti al Geometra Palli Giorgio per compilazione di perizie indirizzata al Capo del Genio Civile di Pavia, Varzi 24 dicembre 1945.</titolo1>
      <luogoed></luogoed>
      <datacompl>1945</datacompl>
      <valb>F</valb>
      <desvalingl>Direct source</desvalingl>
    </Bibliography>
    <Bibliography>
      <codbib>650067</codbib>
      <autore1>*</autore1>
      <titolo1>Archivio Storico Comunale di Varzi, cat.10, cl.9, Lettera del Sindaco del comune di Varzi Grazzi M. all’Ingegnere Capo del Genio Civile di Pavia, Varzi 13 luglio 1945.</titolo1>
      <luogoed></luogoed>
      <datacompl>1945</datacompl>
      <valb>F</valb>
      <desvalingl>Direct source</desvalingl>
    </Bibliography>
    <Bibliography>
      <codbib>650068</codbib>
      <autore1>*</autore1>
      <titolo1>Archivio Storico Comunale di Varzi, cat.10 cl.9, Lettera del Sindaco del comune di Varzi Grazzi M. al Capo del Genio Civile di Pavia Varzi 1945.</titolo1>
      <luogoed>Varzi</luogoed>
      <datacompl>1945</datacompl>
      <valb>F</valb>
      <desvalingl>Direct source</desvalingl>
    </Bibliography>
    <Bibliography>
      <codbib>650069</codbib>
      <autore1>*</autore1>
      <titolo1>Archivio Storico Comunale di Varzi, cat.10, cl.9, Lettera del Sindaco di Varzi Grazzi M. al Comando Alleato di Pavia, Varzi 13 luglio 1945.</titolo1>
      <luogoed></luogoed>
      <datacompl>1945</datacompl>
      <valb>F</valb>
      <desvalingl>Direct source</desvalingl>
    </Bibliography>
    <Bibliography>
      <codbib>650070</codbib>
      <autore1>*</autore1>
      <titolo1>Archivio Storico Comunale di Varzi, cat.10, cl.9, Direzione Didattica di Zavattarello in Varzi, Lettera della Direzione Didattica di Zavattarello in Varzi al Sindaco, Varzi 4 luglio 1945.</titolo1>
      <luogoed>Varzi</luogoed>
      <datacompl>1945</datacompl>
      <valb>F</valb>
      <desvalingl>Direct source</desvalingl>
    </Bibliography>
    <Bibliography>
      <codbib>650071</codbib>
      <autore1>*</autore1>
      <titolo1>Archivio Storico Comunale di Varzi, Terremoto del 29 giugno 1945, Raccolta di Lettere di denuncia di privati per i danni subiti in occasione delle scosse telluriche del 29 giugno 1945.</titolo1>
      <luogoed>Varzi</luogoed>
      <datacompl>1945</datacompl>
      <valb>F</valb>
      <desvalingl>Direct source</desvalingl>
    </Bibliography>
    <Bibliography>
      <codbib>650075</codbib>
      <autore1>*</autore1>
      <titolo1>Archivio Parrocchiale dei Ss.Apostoli Pietro e Paolo di Livelli di Bagnaria, scaff.2, Corrispondenza (1907-1952).</titolo1>
      <luogoed></luogoed>
      <datacompl>1907 - 1952</datacompl>
      <valb>Fn</valb>
      <desvalingl>Negative source</desvalingl>
    </Bibliography>
    <Bibliography>
      <codbib>650078</codbib>
      <autore1>*</autore1>
      <titolo1>Archivio Parrocchiale dei Ss.Apostoli Pietro e Paolo di Livelli di Bagnaria, scaff.2, Registro di cassa (1945-1965).</titolo1>
      <luogoed></luogoed>
      <datacompl>1945 - 1965</datacompl>
      <valb>Fn</valb>
      <desvalingl>Negative source</desvalingl>
    </Bibliography>
    <Bibliography>
      <codbib>650080</codbib>
      <autore1>*</autore1>
      <titolo1>Archivio Comunale di Val di Nizza, cat.10, cl.19, Lettera dell’Ingegnere Capo del Genio Civile di Pavia Mariani G. al Sindaco del comune di Valdinizza, Pavia 20 settembre 1945, con oggetto, danni terremoto edifici scolastici Valdinizza.</titolo1>
      <luogoed></luogoed>
      <datacompl>1945</datacompl>
      <valb>F</valb>
      <desvalingl>Direct source</desvalingl>
    </Bibliography>
    <Bibliography>
      <codbib>650081</codbib>
      <autore1>*</autore1>
      <titolo1>Archivio Comunale di Val di Nizza, cat.10, cl.19, Lettera del Sindaco di Valdinizza al Genio Civile di Pavia, Valdinizza 24 agosto 1946, con oggetto, danni del terremoto da edifici pubblici.</titolo1>
      <luogoed></luogoed>
      <datacompl>1946</datacompl>
      <valb>F</valb>
      <desvalingl>Direct source</desvalingl>
    </Bibliography>
    <Bibliography>
      <codbib>650082</codbib>
      <autore1>*</autore1>
      <titolo1>Archivio Comunale di Val di Nizza, cat.10, cl.19, Lettera del Capo del Genio Civile di Pavia Villa R. al Sindaco di Valdinizza, Pavia 31 ottobre 1946, con oggetto, danni terremoto edifici scolastici.</titolo1>
      <luogoed></luogoed>
      <datacompl>1946</datacompl>
      <valb>F</valb>
      <desvalingl>Direct source</desvalingl>
    </Bibliography>
    <Bibliography>
      <codbib>650083</codbib>
      <autore1>*</autore1>
      <titolo1>Archivio Comunale di Val di Nizza, cat.10, cl.19, Lettera del Capo del Genio Civile di Pavia Villa R. al Sindaco di Valdinizza, Pavia 20 novembre 1946, con oggetto, Buono di Cemento per riparazione scuola.</titolo1>
      <luogoed></luogoed>
      <datacompl>1946</datacompl>
      <valb>F</valb>
      <desvalingl>Direct source</desvalingl>
    </Bibliography>
    <Bibliography>
      <codbib>650084</codbib>
      <autore1>*</autore1>
      <titolo1>Archivio Comunale di Val di Nizza, Deliberazioni della Giunta Municipale del comune di Valdinizza, 1945-1946.</titolo1>
      <luogoed></luogoed>
      <datacompl>1945 - 1946</datacompl>
      <valb>Fn</valb>
      <desvalingl>Negative source</desvalingl>
    </Bibliography>
    <Bibliography>
      <codbib>650085</codbib>
      <autore1>*</autore1>
      <titolo1>Archivio Comunale di Val di Nizza, Deliberazioni del Consiglio Comunale di Valdinizza, 1946-1974.</titolo1>
      <luogoed></luogoed>
      <datacompl>1946 - 1974</datacompl>
      <valb>Fn</valb>
      <desvalingl>Negative source</desvalingl>
    </Bibliography>
    <Bibliography>
      <codbib>650092</codbib>
      <autore1>*</autore1>
      <titolo1>Intervista a don Mario Braghieri parroco di Cecima sul terremoto del 29 giugno 1945 registrata a cura di SGA, Cecima 28 aprile 1984.</titolo1>
      <luogoed></luogoed>
      <datacompl>1984</datacompl>
      <valb>Fi</valb>
      <desvalingl>Indirect source</desvalingl>
    </Bibliography>
    <Bibliography>
      <codbib>650095</codbib>
      <autore1>*</autore1>
      <titolo1>Archivio Comunale di Menconico, Protocollo, 1945-1960.</titolo1>
      <luogoed></luogoed>
      <datacompl>1945 - 1960</datacompl>
      <valb>Fn</valb>
      <desvalingl>Negative source</desvalingl>
    </Bibliography>
    <Bibliography>
      <codbib>650096</codbib>
      <autore1>*</autore1>
      <titolo1>Archivio Comunale di Menconico, Raccolta documenti, cat.5-15, 1944-1949.</titolo1>
      <luogoed></luogoed>
      <datacompl>1944 - 1949</datacompl>
      <valb>Fn</valb>
      <desvalingl>Negative source</desvalingl>
    </Bibliography>
    <Bibliography>
      <codbib>650099</codbib>
      <autore1>*</autore1>
      <titolo1>Archivio Comunale di Romagnese, Deliberazioni del Consiglio Comunale, 1945-1950.</titolo1>
      <luogoed></luogoed>
      <datacompl>1945 - 1950</datacompl>
      <valb>Fn</valb>
      <desvalingl>Negative source</desvalingl>
    </Bibliography>
    <Bibliography>
      <codbib>650100</codbib>
      <autore1>*</autore1>
      <titolo1>Archivio Comunale di Romagnese, Lavori pubblici, Illuminazione, 1945-1948.</titolo1>
      <luogoed></luogoed>
      <datacompl>1945 - 1948</datacompl>
      <valb>Fn</valb>
      <desvalingl>Negative source</desvalingl>
    </Bibliography>
    <Bibliography>
      <codbib>650101</codbib>
      <autore1>*</autore1>
      <titolo1>Archivio Comunale di Romagnese, Immigrazione e sicurezza pubblica, 1945-1950.</titolo1>
      <luogoed></luogoed>
      <datacompl>1945 - 1950</datacompl>
      <valb>Fn</valb>
      <desvalingl>Negative source</desvalingl>
    </Bibliography>
    <Bibliography>
      <codbib>650102</codbib>
      <autore1>*</autore1>
      <titolo1>Archivio Comunale di Romagnese, Pubblica istruzione, Manutenzione edifici scolastici, 1945-1948.</titolo1>
      <luogoed></luogoed>
      <datacompl>1945 - 1948</datacompl>
      <valb>Fn</valb>
      <desvalingl>Negative source</desvalingl>
    </Bibliography>
    <Bibliography>
      <codbib>650103</codbib>
      <autore1>*</autore1>
      <titolo1>Archivio Comunale di Romagnese, Raccalta documenti, Relazioni sui danni causati dalle frane nei paesi di Grotta di Là 1961, e Canavizza 1978.</titolo1>
      <luogoed></luogoed>
      <datacompl>1961 - 1978</datacompl>
      <valb>Fn</valb>
      <desvalingl>Negative source</desvalingl>
    </Bibliography>
    <Bibliography>
      <codbib>650104</codbib>
      <autore1>*</autore1>
      <titolo1>Archivio Parrocchiale di Varzi, Registro di Cassa della parrocchia di Varzi, 1944-1949.</titolo1>
      <luogoed></luogoed>
      <datacompl>1944 - 1949</datacompl>
      <valb>Fn</valb>
      <desvalingl>Negative source</desvalingl>
    </Bibliography>
    <Bibliography>
      <codbib>650105</codbib>
      <autore1>*</autore1>
      <titolo1>Archivio Comunale di Zavattarello, Lavori pubblici, Cantonieri ed edilizia, 1944-1948.</titolo1>
      <luogoed></luogoed>
      <datacompl>1944 - 1948</datacompl>
      <valb>Fn</valb>
      <desvalingl>Negative source</desvalingl>
    </Bibliography>
    <Bibliography>
      <codbib>650106</codbib>
      <autore1>*</autore1>
      <titolo1>Archivio Comunale di Zavattarello, Pubblica istruzione, Incarichi manutenzione edifici scolastici, 1946-1948.</titolo1>
      <luogoed></luogoed>
      <datacompl>1946 - 1948</datacompl>
      <valb>Fn</valb>
      <desvalingl>Negative source</desvalingl>
    </Bibliography>
    <Bibliography>
      <codbib>650107</codbib>
      <autore1>*</autore1>
      <titolo1>Archivio Comunale di Zavattarello, Pubblica sicurezza, 1944-1946.</titolo1>
      <luogoed></luogoed>
      <datacompl>1944 - 1946</datacompl>
      <valb>Fn</valb>
      <desvalingl>Negative source</desvalingl>
    </Bibliography>
    <Bibliography>
      <codbib>650108</codbib>
      <autore1>*</autore1>
      <titolo1>Archivio Comunale di Zavattarello, Corrispondenza oggetti vari, 1945-1948.</titolo1>
      <luogoed></luogoed>
      <datacompl>1945 - 1948</datacompl>
      <valb>Fn</valb>
      <desvalingl>Negative source</desvalingl>
    </Bibliography>
    <Bibliography>
      <codbib>650110</codbib>
      <autore1>*</autore1>
      <titolo1>Archivio Comunale di Zavattarello, Protocollo, 1945-1948.</titolo1>
      <luogoed></luogoed>
      <datacompl>1945 - 1948</datacompl>
      <valb>Fn</valb>
      <desvalingl>Negative source</desvalingl>
    </Bibliography>
    <Bibliography>
      <codbib>650115</codbib>
      <autore1>*</autore1>
      <titolo1>Archivio Comunale di Pozzol Groppo, Raccolta documenti, cat.9-15, 1944-1948.</titolo1>
      <luogoed></luogoed>
      <datacompl>1944 - 1948</datacompl>
      <valb>Fn</valb>
      <desvalingl>Negative source</desvalingl>
    </Bibliography>
    <Bibliography>
      <codbib>650117</codbib>
      <autore1>*</autore1>
      <titolo1>La Provincia Pavese, 1945.07.01, a.1, n.44.</titolo1>
      <luogoed>Pavia</luogoed>
      <datacompl>1945</datacompl>
      <valb>Fi</valb>
      <desvalingl>Indirect source</desvalingl>
    </Bibliography>
    <Bibliography>
      <codbib>650180</codbib>
      <autore1>*</autore1>
      <titolo1>Intervista a don Mario Torre parroco di San Ponzo Semola sul terremoto del 29 giugno 1945 registrata a cura di SGA, San Ponzo Semola 11 aprile 1984.</titolo1>
      <luogoed></luogoed>
      <datacompl>1984</datacompl>
      <valb>Fi</valb>
      <desvalingl>Indirect source</desvalingl>
    </Bibliography>
    <Bibliography>
      <codbib>660005</codbib>
      <autore1>*</autore1>
      <titolo1>Archivio Storico del Comune di Fabbrica Curone, Verbali di Giunta, aprile 1945-ottobre 1952, Verbale di delibera della Giunta comunale relativa al restauro del municipio, Fabbrica Curone 1 dicembre 1945.</titolo1>
      <luogoed></luogoed>
      <datacompl>1945 - 1952</datacompl>
      <valb>F</valb>
      <desvalingl>Direct source</desvalingl>
    </Bibliography>
    <Bibliography>
      <codbib>660006</codbib>
      <autore1>*</autore1>
      <titolo1>Archivio Storico del Comune di Fabbrica Curone, Verbali di Deliberazione della Giunta Municipale, dal 17 ottobre 1942 all’8 novembre 1945.</titolo1>
      <luogoed></luogoed>
      <datacompl>1942 - 1945</datacompl>
      <valb>Fn</valb>
      <desvalingl>Negative source</desvalingl>
    </Bibliography>
    <Bibliography>
      <codbib>660008</codbib>
      <autore1>*</autore1>
      <titolo1>Archivio Storico del Comune di Fabbrica Curone, Verbali di Consiglio, 20 aprile 1946-30 ottobre 1958.</titolo1>
      <luogoed></luogoed>
      <datacompl>1946 - 1958</datacompl>
      <valb>Fn</valb>
      <desvalingl>Negative source</desvalingl>
    </Bibliography>
    <Bibliography>
      <codbib>660009</codbib>
      <autore1>*</autore1>
      <titolo1>Archivio Storico del Comune di Fabbrica Curone, Conti Consultivi, 1943-1948.</titolo1>
      <luogoed></luogoed>
      <datacompl>1943 - 1948</datacompl>
      <valb>Fn</valb>
      <desvalingl>Negative source</desvalingl>
    </Bibliography>
    <Bibliography>
      <codbib>660010</codbib>
      <autore1>*</autore1>
      <titolo1>Archivio Storico del Comune di Garbagna, Verbali di Deliberazione, Registro, 1939-1950.</titolo1>
      <luogoed></luogoed>
      <datacompl>1939 - 1950</datacompl>
      <valb>Fn</valb>
      <desvalingl>Negative source</desvalingl>
    </Bibliography>
    <Bibliography>
      <codbib>660023</codbib>
      <autore1>*</autore1>
      <titolo1>Intervista a don Angelo Bassi parroco di Gremiasco sul terremoto del 29 giugno 1945 registrata a cura di SGA, Gremiasco 9 marzo 1984.</titolo1>
      <luogoed></luogoed>
      <datacompl>1984</datacompl>
      <valb>F</valb>
      <desvalingl>Direct source</desvalingl>
    </Bibliography>
    <Bibliography>
      <codbib>660030</codbib>
      <autore1>*</autore1>
      <titolo1>Archivio Storico del Comune di Borghetto di Borbera, Protocollo, registro, 1945, vol.1.</titolo1>
      <luogoed></luogoed>
      <datacompl>1945</datacompl>
      <valb>Fn</valb>
      <desvalingl>Negative source</desvalingl>
    </Bibliography>
    <Bibliography>
      <codbib>660031</codbib>
      <autore1>*</autore1>
      <titolo1>Archivio Storico del Comune di Borghetto di Borbera, Deliberazioni Consiglio Comunale, 1945.</titolo1>
      <luogoed></luogoed>
      <datacompl>1945</datacompl>
      <valb>Fn</valb>
      <desvalingl>Negative source</desvalingl>
    </Bibliography>
    <Bibliography>
      <codbib>660040</codbib>
      <autore1>*</autore1>
      <titolo1>Archivio Storico del Comune di Grondona, Registro delibere dal 9 gennaio 1937 al 9 giugno 1948.</titolo1>
      <luogoed></luogoed>
      <datacompl>1937 - 1948</datacompl>
      <valb>Fn</valb>
      <desvalingl>Negative source</desvalingl>
    </Bibliography>
    <Bibliography>
      <codbib>660042</codbib>
      <autore1>*</autore1>
      <titolo1>Archivio Storico del Comune di Grondona, Miscellanea "Ante 1947", fasc.2.</titolo1>
      <luogoed></luogoed>
      <datacompl>XX sec.</datacompl>
      <valb>Fn</valb>
      <desvalingl>Negative source</desvalingl>
    </Bibliography>
    <Bibliography>
      <codbib>660052</codbib>
      <autore1>*</autore1>
      <titolo1>Archivio Storico del Comune di Villalvernia, Deliberazioni del Podestà, 1926-1945.</titolo1>
      <luogoed></luogoed>
      <datacompl>1926 - 1945</datacompl>
      <valb>Fn</valb>
      <desvalingl>Negative source</desvalingl>
    </Bibliography>
    <Bibliography>
      <codbib>660066</codbib>
      <autore1>*</autore1>
      <titolo1>Archivio Storico del Comune di San Sebastiano Curone, Deliberazioni del Podestà, 1935-1945.</titolo1>
      <luogoed></luogoed>
      <datacompl>1935 - 1945</datacompl>
      <valb>Fn</valb>
      <desvalingl>Negative source</desvalingl>
    </Bibliography>
    <Bibliography>
      <codbib>710156</codbib>
      <autore1>*</autore1>
      <titolo1>Intervista a don Adamo Accosa parroco di Cella di Varzi sul terremoto del 29 giugno 1945, registrata a cura di SGA, Cella di Varzi 23 marzo 1984.</titolo1>
      <luogoed></luogoed>
      <datacompl>1984</datacompl>
      <valb>Fi</valb>
      <desvalingl>Indirect source</desvalingl>
    </Bibliography>
  </Biblios>
  <Localities/>
  <LocComments>
    <Locality>
      <intpq>VI-VII</intpq>
      <desloc>Bagnaria</desloc>
      <lat_wgs84>44.8268</lat_wgs84>
      <lon_wgs84>9.1238</lon_wgs84>
      <provlet>PV</provlet>
      <nazione>Italy</nazione>
      <intpqnum>6.5</intpqnum>
      <nterr>32310</nterr>
      <nloc_cfti>017134.00</nloc_cfti>
      <desloc_cfti>Bagnaria</desloc_cfti>
      <notesito></notesito>
      <COMM>La scossa fu molto forte e causò gravi lesioni e crolli parziali alle case del paese; una volta della chiesa crollò e le altre vennero gravemente danneggiate; nella canonica cadde un soffitto del piano superiore e si aprirono varie crepe nei muri; il campanile riportò danni ai supporti della campana maggiore, complessivamente i danni alla chiesa ammontarono a 200.000 lire $(650054,050021,650067,650068,650071)$.</COMM>
    </Locality>
    <Locality>
      <intpq>VI-VII</intpq>
      <desloc>Gremiasco</desloc>
      <lat_wgs84>44.7971</lat_wgs84>
      <lon_wgs84>9.1061</lon_wgs84>
      <provlet>AL</provlet>
      <nazione>Italy</nazione>
      <intpqnum>6.5</intpqnum>
      <nterr>32310</nterr>
      <nloc_cfti>008610.00</nloc_cfti>
      <desloc_cfti>Gremiasco</desloc_cfti>
      <notesito></notesito>
      <COMM>La scossa fu molto forte, causò la caduta di camini, lesionò la volta della chiesa e aprì piccole crepe nel campanile, causando notevole spavento nella popolazione $(660023,050021)$.</COMM>
    </Locality>
    <Locality>
      <intpq>VI-VII</intpq>
      <desloc>Ponte Crenna</desloc>
      <lat_wgs84>44.8246</lat_wgs84>
      <lon_wgs84>9.1559</lon_wgs84>
      <provlet>PV</provlet>
      <nazione>Italy</nazione>
      <intpqnum>6.5</intpqnum>
      <nterr>32310</nterr>
      <nloc_cfti>017143.00</nloc_cfti>
      <desloc_cfti>Ponte Crenna</desloc_cfti>
      <notesito></notesito>
      <COMM>La scossa fu molto forte e causò gravi lesioni e crolli parziali in alcuni edifici, una stalla con sovrastante fienile crollò completamente $(080130,650071)$.</COMM>
    </Locality>
    <Locality>
      <intpq>VI-VII</intpq>
      <desloc>Varzi</desloc>
      <lat_wgs84>44.8235</lat_wgs84>
      <lon_wgs84>9.1966</lon_wgs84>
      <provlet>PV</provlet>
      <nazione>Italy</nazione>
      <intpqnum>6.5</intpqnum>
      <nterr>32310</nterr>
      <nloc_cfti>018322.00</nloc_cfti>
      <desloc_cfti>Varzi</desloc_cfti>
      <notesito></notesito>
      <COMM>La scossa fu molto forte e aprì lesioni nelle compagini murarie e nei tetti degli edifici del paese $(650071)$. Danni si verificarono nelle cappelle e nel porticato del cimitero con spostamento e caduta delle tegole di copertura $(650060,650059)$; nella palestra delle scuole comunali e nell’asilo infantile furono aggravate le lesioni provocate dagli eventi bellici precedenti $(650058,650068,650067,650069)$.</COMM>
    </Locality>
    <Locality>
      <intpq>II-III</intpq>
      <desloc>Pavia</desloc>
      <lat_wgs84>45.19</lat_wgs84>
      <lon_wgs84>9.1597</lon_wgs84>
      <provlet>PV</provlet>
      <nazione>Italy</nazione>
      <intpqnum>2.5</intpqnum>
      <nterr>32310</nterr>
      <nloc_cfti>017853.00</nloc_cfti>
      <desloc_cfti>Pavia</desloc_cfti>
      <notesito></notesito>
      <COMM>La scossa fu abbastanza forte e venne registrata dagli strumenti dell’Osservatorio Geofisico della città $(650117,080130)$.</COMM>
    </Locality>
    <Locality>
      <intpq>II-III</intpq>
      <desloc>Torino</desloc>
      <lat_wgs84>45.0711</lat_wgs84>
      <lon_wgs84>7.6737</lon_wgs84>
      <provlet>TO</provlet>
      <nazione>Italy</nazione>
      <intpqnum>2.5</intpqnum>
      <nterr>32310</nterr>
      <nloc_cfti>002356.00</nloc_cfti>
      <desloc_cfti>Torino</desloc_cfti>
      <notesito></notesito>
      <COMM>La scossa fu leggera $(080130)$.</COMM>
    </Locality>
  </LocComments>
  <Seqs/>
</Quake>
