<?xml version="1.0" encoding="ISO-8859-1"?>
<Quake alone="true">
  <Details>
    <Detail>
      <cat>ITA</cat>
      <nterr>04717</nterr>
      <nperiod>000959</nperiod>
      <datanum>17940629</datanum>
      <data_label>1794 06 29</data_label>
      <anno>1794</anno>
      <mese>06</mese>
      <giorno>29</giorno>
      <time_label>-</time_label>
      <ora>-9</ora>
      <minu>-9</minu>
      <sec>-9</sec>
      <lat>45.533</lat>
      <lon>11.55</lon>
      <rel>F</rel>
      <level>S</level>
      <io>0</io>
      <imax>0</imax>
      <npun>0</npun>
      <ee_nt>0</ee_nt>
      <ee_np>0</ee_np>
      <mm>0</mm>
      <earthquakelocation>Vicenza</earthquakelocation>
      <epicenter_type>-</epicenter_type>
      <country>Italy</country>
      <flagcomments>3</flagcomments>
      <flagfalseeq>1</flagfalseeq>
      <new2018></new2018>
    </Detail>
  </Details>
  <Comments/>
  <Biblios>
    <Bibliography>
      <codbib>021244</codbib>
      <autore1>SGA</autore1>
      <titolo1>Studi ed indagini per l’accertamento della idoneità tecnica delle aree suscettibili di insediamento di impianti nucleari. Regione Lombardia, Area San Benedetto Po. Indagini di sismica storica: rapporto finale (inedito per ENEL).</titolo1>
      <luogoed></luogoed>
      <datacompl>1985</datacompl>
      <valb>Bs</valb>
      <desvalingl>Scientific bibliography</desvalingl>
    </Bibliography>
    <Bibliography>
      <codbib>050398</codbib>
      <autore1>Piovene G.</autore1>
      <titolo1>Cronaca dei terremoti a Vicenza, in "Annali dell’Ufficio Centrale Meteorologico e Geodinamico Italiano", s.II, vol.8, a.1886, parte 4, pp.45-57.</titolo1>
      <luogoed>Roma</luogoed>
      <datacompl>1888</datacompl>
      <valb>C</valb>
      <desvalingl>Catalogue</desvalingl>
    </Bibliography>
    <Bibliography>
      <codbib>051293</codbib>
      <autore1>Bernardis G., Giorgetti F., Nieto D. e Slejko D.</autore1>
      <titolo1>Correction to the Earthquakes Catalogue for Eastern Alps Region.</titolo1>
      <luogoed>Trieste</luogoed>
      <datacompl>1978</datacompl>
      <valb>C</valb>
      <desvalingl>Catalogue</desvalingl>
    </Bibliography>
    <Bibliography>
      <codbib>500005</codbib>
      <autore1>*</autore1>
      <titolo1>Biblioteca Civica Bertoliana di Vicenza, Manoscritti Gonzati, 23.10.15-17 (=1673-1675), G.Favetta, Memorie di quanto successe nella città di Vicenza dall’anno 1702 sino all’anno 1816, 3 voll, sec.XIX.</titolo1>
      <luogoed></luogoed>
      <datacompl>XVIII sec. - XIX sec.</datacompl>
      <valb>F</valb>
      <desvalingl>Direct source</desvalingl>
    </Bibliography>
  </Biblios>
  <Localities/>
  <LocComments/>
  <Seqs/>
</Quake>
