<?xml version="1.0" encoding="ISO-8859-1"?>
<Quake alone="true">
  <Details>
    <Detail>
      <cat>MED</cat>
      <nterr>M2033</nterr>
      <nperiod>M20030</nperiod>
      <datanum>10680318</datanum>
      <data_label>1068 03 18</data_label>
      <anno>1068</anno>
      <mese>03</mese>
      <giorno>18</giorno>
      <time_label>06:30</time_label>
      <ora>06</ora>
      <minu>30</minu>
      <sec></sec>
      <lat>29.55</lat>
      <lon>34.95</lon>
      <rel></rel>
      <level></level>
      <io>9</io>
      <imax>10</imax>
      <npun>13</npun>
      <ee_nt>3</ee_nt>
      <ee_np>0</ee_np>
      <mm>7.2</mm>
      <earthquakelocation>Elat</earthquakelocation>
      <epicenter_type>Calculated epicentre</epicenter_type>
      <country>Israel</country>
      <flagcomments></flagcomments>
      <flagfalseeq></flagfalseeq>
    </Detail>
  </Details>
  <Comments/>
  <Biblios/>
  <Localities/>
  <LocComments>
    <Locality>
      <intpq>X</intpq>
      <desloc>Elat</desloc>
      <lat_wgs84>29.55</lat_wgs84>
      <lon_wgs84>34.95</lon_wgs84>
      <provlet></provlet>
      <nazione>Israel</nazione>
      <intpqnum>10</intpqnum>
      <nterr>M2033</nterr>
      <nloc_cfti>082026.00</nloc_cfti>
      <desloc_cfti>Elat</desloc_cfti>
      <notesito>Aylat - Aila</notesito>
      <COMM/>
    </Locality>
    <Locality>
      <intpq>VII-VIII</intpq>
      <desloc>Al-Marwa</desloc>
      <lat_wgs84>26.683</lat_wgs84>
      <lon_wgs84>36.917</lon_wgs84>
      <provlet></provlet>
      <nazione>Saudi Arabia</nazione>
      <intpqnum>7.5</intpqnum>
      <nterr>M2033</nterr>
      <nloc_cfti>082012.00</nloc_cfti>
      <desloc_cfti>Al-Marwa</desloc_cfti>
      <notesito></notesito>
      <COMM/>
    </Locality>
    <Locality>
      <intpq>VII-VIII</intpq>
      <desloc>Badr</desloc>
      <lat_wgs84>23.781</lat_wgs84>
      <lon_wgs84>38.793</lon_wgs84>
      <provlet></provlet>
      <nazione>Saudi Arabia</nazione>
      <intpqnum>7.5</intpqnum>
      <nterr>M2033</nterr>
      <nloc_cfti>082029.00</nloc_cfti>
      <desloc_cfti>Badr</desloc_cfti>
      <notesito></notesito>
      <COMM/>
    </Locality>
    <Locality>
      <intpq>VII-VIII</intpq>
      <desloc>Khaybar</desloc>
      <lat_wgs84>25.7</lat_wgs84>
      <lon_wgs84>39.29</lon_wgs84>
      <provlet></provlet>
      <nazione>Saudi Arabia</nazione>
      <intpqnum>7.5</intpqnum>
      <nterr>M2033</nterr>
      <nloc_cfti>082292.00</nloc_cfti>
      <desloc_cfti>Khaybar</desloc_cfti>
      <notesito></notesito>
      <COMM/>
    </Locality>
    <Locality>
      <intpq>VII-VIII</intpq>
      <desloc>Wadi al-Qura</desloc>
      <lat_wgs84>26.53</lat_wgs84>
      <lon_wgs84>37.02</lon_wgs84>
      <provlet></provlet>
      <nazione>Saudi Arabia</nazione>
      <intpqnum>7.5</intpqnum>
      <nterr>M2033</nterr>
      <nloc_cfti>082230.00</nloc_cfti>
      <desloc_cfti>Wadi al-Qura</desloc_cfti>
      <notesito></notesito>
      <COMM/>
    </Locality>
    <Locality>
      <intpq>VII-VIII</intpq>
      <desloc>Wadi al-Safra'</desloc>
      <lat_wgs84>24.033</lat_wgs84>
      <lon_wgs84>38.933</lon_wgs84>
      <provlet></provlet>
      <nazione>Saudi Arabia</nazione>
      <intpqnum>7.5</intpqnum>
      <nterr>M2033</nterr>
      <nloc_cfti>082231.00</nloc_cfti>
      <desloc_cfti>Wadi al-Safra'</desloc_cfti>
      <notesito></notesito>
      <COMM/>
    </Locality>
    <Locality>
      <intpq>VII-VIII</intpq>
      <desloc>Yanbu' al Bahr</desloc>
      <lat_wgs84>24.083</lat_wgs84>
      <lon_wgs84>38.05</lon_wgs84>
      <provlet></provlet>
      <nazione>Saudi Arabia</nazione>
      <intpqnum>7.5</intpqnum>
      <nterr>M2033</nterr>
      <nloc_cfti>082360.00</nloc_cfti>
      <desloc_cfti>Yanbu' al Bahr</desloc_cfti>
      <notesito></notesito>
      <COMM/>
    </Locality>
    <Locality>
      <intpq>VII</intpq>
      <desloc>Alexandria</desloc>
      <lat_wgs84>31.2</lat_wgs84>
      <lon_wgs84>29.92</lon_wgs84>
      <provlet></provlet>
      <nazione>Egypt</nazione>
      <intpqnum>7</intpqnum>
      <nterr>M2033</nterr>
      <nloc_cfti>082017.00</nloc_cfti>
      <desloc_cfti>Alexandria</desloc_cfti>
      <notesito></notesito>
      <COMM/>
    </Locality>
    <Locality>
      <intpq>VII</intpq>
      <desloc>Tinnis</desloc>
      <lat_wgs84>31.2</lat_wgs84>
      <lon_wgs84>32.233</lon_wgs84>
      <provlet></provlet>
      <nazione>Egypt</nazione>
      <intpqnum>7</intpqnum>
      <nterr>M2033</nterr>
      <nloc_cfti>082216.00</nloc_cfti>
      <desloc_cfti>Tinnis</desloc_cfti>
      <notesito></notesito>
      <COMM/>
    </Locality>
    <Locality>
      <intpq>VI</intpq>
      <desloc>Cairo</desloc>
      <lat_wgs84>30.05</lat_wgs84>
      <lon_wgs84>31.25</lon_wgs84>
      <provlet></provlet>
      <nazione>Egypt</nazione>
      <intpqnum>6</intpqnum>
      <nterr>M2033</nterr>
      <nloc_cfti>082099.00</nloc_cfti>
      <desloc_cfti>Cairo</desloc_cfti>
      <notesito></notesito>
      <COMM/>
    </Locality>
    <Locality>
      <intpq>VI</intpq>
      <desloc>Medina</desloc>
      <lat_wgs84>24.47</lat_wgs84>
      <lon_wgs84>39.61</lon_wgs84>
      <provlet></provlet>
      <nazione>Saudi Arabia</nazione>
      <intpqnum>6</intpqnum>
      <nterr>M2033</nterr>
      <nloc_cfti>082136.00</nloc_cfti>
      <desloc_cfti>Medina</desloc_cfti>
      <notesito></notesito>
      <COMM/>
    </Locality>
    <Locality>
      <intpq>F</intpq>
      <desloc>Kufa</desloc>
      <lat_wgs84>32.033</lat_wgs84>
      <lon_wgs84>44.4</lon_wgs84>
      <provlet></provlet>
      <nazione>Iraq</nazione>
      <intpqnum>4.6</intpqnum>
      <nterr>M2033</nterr>
      <nloc_cfti>082113.00</nloc_cfti>
      <desloc_cfti>Kufa</desloc_cfti>
      <notesito>Al-Kufah</notesito>
      <COMM/>
    </Locality>
    <Locality>
      <intpq>III</intpq>
      <desloc>Baghdad</desloc>
      <lat_wgs84>33.34</lat_wgs84>
      <lon_wgs84>44.39</lon_wgs84>
      <provlet></provlet>
      <nazione>Iraq</nazione>
      <intpqnum>3</intpqnum>
      <nterr>M2033</nterr>
      <nloc_cfti>082030.00</nloc_cfti>
      <desloc_cfti>Baghdad</desloc_cfti>
      <notesito></notesito>
      <COMM/>
    </Locality>
  </LocComments>
  <Seqs/>
</Quake>
